sensorobjectlibrary/Sol.py
sensorobjectlibrary/SolDefines.py
sensorobjectlibrary/SolExceptions.py
sensorobjectlibrary/SolUtils.py
sensorobjectlibrary/__init__.py
sensorobjectlibrary/__version__.py
sensorobjectlibrary/hr_parser.py
sensorobjectlibrary-1.8.0.0.dist-info/LICENSE
sensorobjectlibrary-1.8.0.0.dist-info/METADATA
sensorobjectlibrary-1.8.0.0.dist-info/WHEEL
sensorobjectlibrary-1.8.0.0.dist-info/top_level.txt
sensorobjectlibrary-1.8.0.0.dist-info/RECORD
