Metadata-Version: 2.1
Name: sensorobjectlibrary
Version: 1.8.0.0
Summary: The Sensor Object Library
Home-page: https://github.com/realms-team/sol
Author: Thomas Watteyne, Keoma Brun, Sami Malek, Ziran Zhang
Author-email: keoma.brun@inria.fr
License: Copyright (c) 2018, Inria and Regent of the University of California.
Requires-Dist: pyserial (>=3.4)
